pydesignflow/__init__.py
pydesignflow/ansiterm.py
pydesignflow/block.py
pydesignflow/cli.py
pydesignflow/errors.py
pydesignflow/filemgmt.py
pydesignflow/flow.py
pydesignflow/monitor.py
pydesignflow/result.py
pydesignflow/session.py
pydesignflow/shortcut.py
pydesignflow/sphinx_ext.py
pydesignflow/target.py
pydesignflow/task.py
pydesignflow/version.py
pydesignflow-0.4.3.dist-info/licenses/LICENSE
pydesignflow-0.4.3.dist-info/METADATA
pydesignflow-0.4.3.dist-info/WHEEL
pydesignflow-0.4.3.dist-info/entry_points.txt
pydesignflow-0.4.3.dist-info/top_level.txt
pydesignflow-0.4.3.dist-info/RECORD
