Metadata-Version: 2.4
Name: pydesignflow
Version: 0.4.3
Summary: Micro-Framework for FPGA / VLSI Design Flow in Python
Maintainer-email: Tobias Kaiser <mail@tb-kaiser.de>
License-Expression: Apache-2.0
Project-URL: Homepage, https://github.com/TobiasKaiser/pydesignflow
Project-URL: Documentation, https://pydesignflow.readthedocs.io
Classifier: Programming Language :: Python :: 3
Classifier: Topic :: Scientific/Engineering :: Electronic Design Automation (EDA)
Requires-Python: >=3.8
License-File: LICENSE
Requires-Dist: tabulate>=0.8.0
Provides-Extra: argcomplete
Requires-Dist: argcomplete>=3.6.2; extra == "argcomplete"
Dynamic: license-file
